langgraph_crosschain/__init__.py
langgraph_crosschain/exceptions.py
langgraph_crosschain/logging.py
langgraph_crosschain/py.typed
langgraph_crosschain/communication/__init__.py
langgraph_crosschain/communication/message_router.py
langgraph_crosschain/core/__init__.py
langgraph_crosschain/core/chain_registry.py
langgraph_crosschain/core/cross_chain_node.py
langgraph_crosschain/routing/__init__.py
langgraph_crosschain/state/__init__.py
langgraph_crosschain/state/shared_state.py
langgraph_crosschain/utils/__init__.py
langgraph_crosschain/utils/decorators.py
langgraph_crosschain/utils/validators.py
langgraph_crosschain-0.1.2.dist-info/licenses/LICENSE
langgraph_crosschain-0.1.2.dist-info/METADATA
langgraph_crosschain-0.1.2.dist-info/WHEEL
langgraph_crosschain-0.1.2.dist-info/top_level.txt
langgraph_crosschain-0.1.2.dist-info/RECORD
