Metadata-Version: 2.4
Name: langgraph-crosschain
Version: 0.1.2
Summary: Cross-chain node communication framework for LangGraph - Enable direct node-to-node communication across multiple LangGraph chains
Home-page: https://github.com/karthyick/langgraph-crosschain
Author: Karthick Raja M
Author-email: Karthick <karthickrajam18@gmail.com>
License: MIT
Project-URL: Homepage, https://github.com/karthyick/langgraph-crosschain
Project-URL: Documentation, https://github.com/karthyick/langgraph-crosschain#readme
Project-URL: Repository, https://github.com/karthyick/langgraph-crosschain.git
Project-URL: Bug Tracker, https://github.com/karthyick/langgraph-crosschain/issues
Project-URL: Source Code, https://github.com/karthyick/langgraph-crosschain
Keywords: langgraph,langchain,cross-chain,multi-agent,agent-orchestration,distributed-agents,ai,llm,agent-communication,chain-registry
Classifier: Development Status :: 4 - Beta
Classifier: Intended Audience :: Developers
Classifier: License :: OSI Approved :: MIT License
Classifier: Operating System :: OS Independent
Classifier: Programming Language :: Python :: 3
Classifier: Programming Language :: Python :: 3.9
Classifier: Programming Language :: Python :: 3.10
Classifier: Programming Language :: Python :: 3.11
Classifier: Programming Language :: Python :: 3.12
Classifier: Topic :: Software Development :: Libraries :: Python Modules
Classifier: Topic :: Scientific/Engineering :: Artificial Intelligence
Classifier: Topic :: Software Development :: Libraries :: Application Frameworks
Classifier: Framework :: AsyncIO
Requires-Python: >=3.9
License-File: LICENSE
Requires-Dist: langgraph<1.0.0,>=0.2.0
Requires-Dist: langchain<2.0.0,>=0.1.0
Requires-Dist: pydantic<3.0.0,>=2.0.0
Requires-Dist: typing-extensions<5.0.0,>=4.0.0
Provides-Extra: dev
Requires-Dist: pytest>=7.0.0; extra == "dev"
Requires-Dist: pytest-cov>=4.0.0; extra == "dev"
Requires-Dist: pytest-asyncio>=0.21.0; extra == "dev"
Requires-Dist: black>=23.0.0; extra == "dev"
Requires-Dist: ruff>=0.1.0; extra == "dev"
Requires-Dist: mypy>=1.0.0; extra == "dev"
Requires-Dist: pre-commit>=3.0.0; extra == "dev"
Requires-Dist: twine>=4.0.0; extra == "dev"
Requires-Dist: build>=0.10.0; extra == "dev"
Provides-Extra: docs
Requires-Dist: sphinx>=7.0.0; extra == "docs"
Requires-Dist: sphinx-rtd-theme>=1.3.0; extra == "docs"
Requires-Dist: sphinx-autodoc-typehints>=1.24.0; extra == "docs"
Dynamic: license-file
